[{"name":"4","items":[{"title":"fgfhfg","text":"test111"},{"title":"gfgfggfgfggfgfggfgfggfgfggfgfggfgfggfgfggfgfggfgfggfgfggfgfggfgfggfgfggfgfggfgfggfgfggfgfggfgfggfgfggfgfggfgfggfgfggfgfggfgfggfgfggfgfggfgfggfgfggfgfggfgfggfgfggfgfggfgfggfgfggfgfggfgfg","text":null}]},{"name":"2","items":[{"title":"fghdfghfdghfghg","text":"fdgsdfghfghgf"},{"title":"ghfghf","text":null}]},{"name":"1","items":[{"title":"dsfsd","text":null},{"title":"dfsdf","text":null}]},{"name":"fdgdfgd","items":[]},{"name":"5","items":[]},{"name":"3","items":[]},{"name":"test","items":[]},{"name":"test1","items":[]},{"name":"test","items":[{"title":"fdgfgdf","text":null},{"title":"fgfd","text":null},{"title":"dfgsd","text":null},{"title":"fdsfgd","text":null}]},{"name":"test2","items":[]},{"name":"test3","items":[]},{"name":"test4","items":[]},{"name":"test5","items":[]},{"name":"test6","items":[]},{"name":"test7","items":[]},{"name":"rter","items":[]},{"name":"rtertfdgfdg","items":[]},{"name":"fgdfdsfg","items":[]}]